tree_sitter_ql/__init__.pyi
tree_sitter_ql/binding.c
tree_sitter_ql/__init__.py
tree_sitter_ql/py.typed
tree_sitter_ql/_binding.abi3.so
tree_sitter_ql/queries/tags.scm
tree_sitter_ql/queries/highlights.scm
tree_sitter_ql-0.23.1.dist-info/RECORD
tree_sitter_ql-0.23.1.dist-info/LICENSE
tree_sitter_ql-0.23.1.dist-info/WHEEL
tree_sitter_ql-0.23.1.dist-info/top_level.txt
tree_sitter_ql-0.23.1.dist-info/METADATA
